swahili/__init__.py
swahili-1.0.0.dist-info/METADATA
swahili-1.0.0.dist-info/WHEEL
swahili-1.0.0.dist-info/top_level.txt
swahili-1.0.0.dist-info/RECORD
