Metadata-Version: 2.1
Name: swahili
Version: 1.0.0
Summary: Natural Language Processing (NLP) Library for Swahili (Kiswahili) Language
Home-page: UNKNOWN
Author-email: emma.minga@yahoo.com
License: UNKNOWN
Platform: UNKNOWN
Classifier: Development Status :: 3 - Alpha
Classifier: Intended Audience :: Developers
Classifier: License :: OSI Approved :: MIT License
Classifier: Programming Language :: Python :: 3.7
Classifier: Programming Language :: Python :: 3.8
Classifier: Programming Language :: Python :: 3.9
Requires-Dist: numpy (>=1.16.0)
Requires-Dist: pandas (>=0.24.0)
